Metadata-Version: 2.1
Name: markdown-autodirection
Version: 0.3
Summary: Extension for markdown package to set paragraph direction to `auto`
Home-page: https://github.com/aliva/python-markdown-autodirection/
License: BSD 3-Clause License
Platform: UNKNOWN
